{
  "calendars": [],
  "fieldFormat": "dataview",
  "muted": false,
  "timerEvent": "notification",
  "inbox": null,
  "search": "",
  "taskSearch": "",
  "fileOrder": [
    "schedule.md"
  ],
  "customStatus": {
    "include": false,
    "statuses": "-"
  },
  "showCompleted": true,
  "groupBy": "path",
  "dayStartEnd": [
    0,
    24
  ],
  "twentyFourHourFormat": false,
  "filterFunction": "",
  "addTaskToEnd": true,
  "extendBlocks": false,
  "hideTimes": false,
  "borders": true,
  "viewMode": "day",
  "scheduledSubtasks": true,
  "openInMain": false
}